mlo_co2/__init__.py
mlo_co2/mlo_co2.py
mlo_co2-0.4.dist-info/LICENSE
mlo_co2-0.4.dist-info/METADATA
mlo_co2-0.4.dist-info/WHEEL
mlo_co2-0.4.dist-info/top_level.txt
mlo_co2-0.4.dist-info/RECORD
