Metadata-Version: 2.1
Name: mlo-co2
Version: 0.4
Summary: Scrape CO2 data from Mauna Loa Observatory off of NOAA Earth Science Research Lab
Home-page: https://github.com/kylepollina/mlo_co2
Author: Kyle Pollina
Author-email: kylepollina@pm.me
License: UNKNOWN
Platform: UNKNOWN
Classifier: Programming Language :: Python :: 3.8
Classifier: Programming Language :: Python :: 3.9
Requires-Python: >=3.8
Requires-Dist: requests
